web/__init__.py
web/dao.py
web/dto.py
web/middlewares.py
web_utility-0.0.3.dist-info/METADATA
web_utility-0.0.3.dist-info/WHEEL
web_utility-0.0.3.dist-info/top_level.txt
web_utility-0.0.3.dist-info/RECORD
