Metadata-Version: 2.1
Name: web-utility
Version: 0.0.3
Summary: Personal web application utility
Home-page: https://github.com/driscollis/arithmetic
Author: Mihael Macuka
Author-email: mihaelmacuka2@gmail.com
Classifier: Programming Language :: Python :: 3
Classifier: License :: OSI Approved :: MIT License
Classifier: Operating System :: OS Independent
Requires-Python: >=3.11
